sanic_openapi3/__init__.py
sanic_openapi3/definitions.py
sanic_openapi3/main.py
sanic_openapi3/openapi.py
sanic_openapi3/security.py
sanic_openapi3/types.py
sanic_openapi3-0.0.2.dist-info/METADATA
sanic_openapi3-0.0.2.dist-info/RECORD
sanic_openapi3-0.0.2.dist-info/WHEEL
sanic_openapi3-0.0.2.dist-info/top_level.txt
