Metadata-Version: 2.1
Name: sanic-openapi3
Version: 0.0.2
Summary: OpenAPI v3 support for Sanic
Home-page: https://github.com/zloyuser/sanic-openapi3
Author: Anton Shabouta
Author-email: zloyusr@gmail.com
License: UNKNOWN
Platform: UNKNOWN
Classifier: Programming Language :: Python :: 3
Classifier: License :: OSI Approved :: MIT License
Classifier: Operating System :: OS Independent
